<?xml version="1.0" encoding="utf-8"?>
<lfm status="ok">
<artist>
  <name>Lady Gaga</name>
  <mbid></mbid>
  <url>http://www.last.fm/music/Lady+Gaga</url>
  <image size="small">http://userserve-ak.last.fm/serve/34/37941489.png</image>
  <image size="medium">http://userserve-ak.last.fm/serve/64/37941489.png</image>
  <image size="large">http://userserve-ak.last.fm/serve/126/37941489.png</image>
  <image size="extralarge">http://userserve-ak.last.fm/serve/252/37941489.png</image>
  <image size="mega">http://userserve-ak.last.fm/serve/500/37941489/Lady+Gaga+Rainbow.png</image>
  <streamable>1</streamable>
  <stats>
    <listeners>1939214</listeners>
    <playcount>90834888</playcount>
      </stats>

  <similar>
	    <artist>
	  <name>Ke$ha</name>
	  <url>http://www.last.fm/music/Ke%24ha</url>
	  <image size="small">http://userserve-ak.last.fm/serve/34/54313623.png</image>
	  <image size="medium">http://userserve-ak.last.fm/serve/64/54313623.png</image>
	  <image size="large">http://userserve-ak.last.fm/serve/126/54313623.png</image>
	  <image size="extralarge">http://userserve-ak.last.fm/serve/252/54313623.png</image>
	  <image size="mega">http://userserve-ak.last.fm/serve/500/54313623/Keha+Cannibal+Promo+PNG.png</image>
	</artist>
    <artist>
	  <name>Katy Perry</name>
	  <url>http://www.last.fm/music/Katy+Perry</url>
	  <image size="small">http://userserve-ak.last.fm/serve/34/45305149.png</image>
	  <image size="medium">http://userserve-ak.last.fm/serve/64/45305149.png</image>
	  <image size="large">http://userserve-ak.last.fm/serve/126/45305149.png</image>
	  <image size="extralarge">http://userserve-ak.last.fm/serve/252/45305149.png</image>
	  <image size="mega">http://userserve-ak.last.fm/serve/_/45305149/Katy+Perry+++PNG.png</image>
	</artist>
    <artist>
	  <name>Rihanna</name>
	  <url>http://www.last.fm/music/Rihanna</url>
	  <image size="small">http://userserve-ak.last.fm/serve/34/53023109.png</image>
	  <image size="medium">http://userserve-ak.last.fm/serve/64/53023109.png</image>
	  <image size="large">http://userserve-ak.last.fm/serve/126/53023109.png</image>
	  <image size="extralarge">http://userserve-ak.last.fm/serve/252/53023109.png</image>
	  <image size="mega">http://userserve-ak.last.fm/serve/_/53023109/Rihanna.png</image>
	</artist>
    <artist>
	  <name>Simon Curtis</name>
	  <url>http://www.last.fm/music/Simon+Curtis</url>
	  <image size="small">http://userserve-ak.last.fm/serve/34/43904351.png</image>
	  <image size="medium">http://userserve-ak.last.fm/serve/64/43904351.png</image>
	  <image size="large">http://userserve-ak.last.fm/serve/126/43904351.png</image>
	  <image size="extralarge">http://userserve-ak.last.fm/serve/252/43904351.png</image>
	  <image size="mega">http://userserve-ak.last.fm/serve/500/43904351/Simon+Curtis+8Bit+Heart+Promo+Picture.png</image>
	</artist>
    <artist>
	  <name>Christina Aguilera</name>
	  <url>http://www.last.fm/music/Christina+Aguilera</url>
	  <image size="small">http://userserve-ak.last.fm/serve/34/53985223.png</image>
	  <image size="medium">http://userserve-ak.last.fm/serve/64/53985223.png</image>
	  <image size="large">http://userserve-ak.last.fm/serve/126/53985223.png</image>
	  <image size="extralarge">http://userserve-ak.last.fm/serve/252/53985223.png</image>
	  <image size="mega">http://userserve-ak.last.fm/serve/_/53985223/Christina+Aguilera+XTINAPNG.png</image>
	</artist>
  </similar>
    <tags>
        <tag>
	  <name>pop</name>
	  <url>http://www.last.fm/tag/pop</url>
	</tag>
        <tag>
	  <name>dance</name>
	  <url>http://www.last.fm/tag/dance</url>
	</tag>
        <tag>
	  <name>electronic</name>
	  <url>http://www.last.fm/tag/electronic</url>
	</tag>
        <tag>
	  <name>female vocalists</name>
	  <url>http://www.last.fm/tag/female%20vocalists</url>
	</tag>
        <tag>
	  <name>female vocalist</name>
	  <url>http://www.last.fm/tag/female%20vocalist</url>
	</tag>
      </tags>
      <bio>
    <published>Fri, 29 Oct 2010 19:30:25 +0000</published>
    <summary><![CDATA[Stefani Joanne Angelina Germanotta (born March 28, 1986), who performs under the stage name Lady Gaga, is a singer, songwriter and musician from New York City, New York, United States.   Before Gaga adopted her stage name she was in a band called <a href="http://www.last.fm/music/Stefani+Germanotta+Band" class="bbcode_artist">Stefani Germanotta Band</a>. She released her first EP, &quot;Red and Blue&quot;, in early 2006. The following year, music producer Rob Fusari dubbed her Lady Gaga, inspired by the <a href="http://www.last.fm/music/Queen" class="bbcode_artist">Queen</a> song &quot;Radio Gaga&quot;. After this she recorded her first two songs as Lady Gaga (Fever and Wonderful) on Def Jam records, but was later let go. ]]></summary>
    <content><![CDATA[Stefani Joanne Angelina Germanotta (born March 28, 1986), who performs under the stage name Lady Gaga, is a singer, songwriter and musician from New York City, New York, United States.   Before Gaga adopted her stage name she was in a band called <a href="http://www.last.fm/music/Stefani+Germanotta+Band" class="bbcode_artist">Stefani Germanotta Band</a>. She released her first EP, &quot;Red and Blue&quot;, in early 2006. The following year, music producer Rob Fusari dubbed her Lady Gaga, inspired by the <a href="http://www.last.fm/music/Queen" class="bbcode_artist">Queen</a> song &quot;Radio Gaga&quot;. After this she recorded her first two songs as Lady Gaga (Fever and Wonderful) on Def Jam records, but was later let go.  She began her career as a songwriter for some of pop music's biggest stars, including <a href="http://www.last.fm/music/Fergie" class="bbcode_artist">Fergie</a>, <a href="http://www.last.fm/music/+noredirect/Pussycat+Dolls" class="bbcode_artist">Pussycat Dolls</a>, <a href="http://www.last.fm/music/Britney+Spears" class="bbcode_artist">Britney Spears</a> and <a href="http://www.last.fm/music/New+Kids+on+the+Block" class="bbcode_artist">New Kids on the Block</a>, as well as American singer and producer <a href="http://www.last.fm/music/Akon" class="bbcode_artist">Akon</a>. After Akon recognized that Gaga also had vocal talent, he signed her to a joint deal with his own label, Kon Live Distribution, and then she started to work on her own new material for her debut album.  Gaga released &quot;The Fame&quot; in 2008, which she explained was &quot;about how anyone can feel famous.&quot; To date, the album has spawned the international number one hit singles &quot;Just Dance&quot; (nominated for Best Dance Recording at the 51st Grammy Awards) and &quot;Poker Face.&quot; The Fame then went Diamond in February 2010, Selling over 12 million copies worldwide.  She then continued to release a new album 1 year later, &quot;The Fame Monster&quot;, which she wasn't intending to make at first. She released &quot;Bad Romance&quot; as the first single, and has been nominated for dozens of awards all over the world. After The Fame Monster was released she released two more singles &quot;Telephone (feat. Beyonce)&quot; and &quot;Alejandro&quot;. She released &quot;Dance in the Dark&quot; as a promotional single, but only released it in Australia, New Zealand and France. She has been touring almost constantly since &quot;The Fame Monster&quot; was released, referring to her shows as The Monster Ball.  Lady Gaga announced her new album name, &quot;Born This Way&quot; at the 2010 MTV VMAs. It is set to be released in 2011, an official date has not been set yet. 
    
User-contributed text is available under the Creative Commons By-SA License and may also be available under the GNU FDL.]]></content>
  </bio>
  </artist></lfm>
